clock/__init__.py
clock/dayclock.py
termclock-1.1.0.dist-info/METADATA
termclock-1.1.0.dist-info/WHEEL
termclock-1.1.0.dist-info/entry_points.txt
termclock-1.1.0.dist-info/top_level.txt
termclock-1.1.0.dist-info/RECORD
