Metadata-Version: 2.1
Name: termclock
Version: 1.1.0
Summary: UNKNOWN
Author: Cargo
License: UNKNOWN
Platform: UNKNOWN
Requires-Dist: click
